<?xml version="1.0" encoding="UTF-8" ?>
<adfc-config xmlns="http://xmlns.oracle.com/adf/controller" version="1.2">
  <managed-bean id="__1">
    <managed-bean-name>backing_Test_Hang_Hoa</managed-bean-name>
    <managed-bean-class>view.backing.Test_Hang_Hoa</managed-bean-class>
    <managed-bean-scope>backingBean</managed-bean-scope>
    <!--oracle-jdev-comment:managed-bean-jsp-link:1Test_Hang_Hoa.jspx-->
  </managed-bean>
  <managed-bean id="__2">
    <managed-bean-name>backing_main</managed-bean-name>
    <managed-bean-class>view.backing.Main</managed-bean-class>
    <managed-bean-scope>backingBean</managed-bean-scope>
    <!--oracle-jdev-comment:managed-bean-jsp-link:1main.jspx-->
  </managed-bean>
  <managed-bean id="__3">
    <managed-bean-name>backing_TestHangHoa</managed-bean-name>
    <managed-bean-class>view.backing.TestHangHoa</managed-bean-class>
    <managed-bean-scope>backingBean</managed-bean-scope>
    <!--oracle-jdev-comment:managed-bean-jsp-link:1TestHangHoa.jspx-->
  </managed-bean>
  <managed-bean id="__4">
    <managed-bean-name>backing_DanhMucLoaiHang</managed-bean-name>
    <managed-bean-class>view.backing.DanhMucLoaiHang</managed-bean-class>
    <managed-bean-scope>backingBean</managed-bean-scope>
    <!--oracle-jdev-comment:managed-bean-jsp-link:1DanhMucLoaiHang.jspx-->
  </managed-bean>
  <managed-bean id="__5">
    <managed-bean-name>backing_DanhMucHangHoa</managed-bean-name>
    <managed-bean-class>view.backing.DanhMucHangHoa</managed-bean-class>
    <managed-bean-scope>backingBean</managed-bean-scope>
    <!--oracle-jdev-comment:managed-bean-jsp-link:1DanhMucHangHoa.jspx-->
  </managed-bean>
  <managed-bean id="__6">
    <managed-bean-name>backing_DanhucDonViBanHang</managed-bean-name>
    <managed-bean-class>view.backing.DanhucDonViBanHang</managed-bean-class>
    <managed-bean-scope>backingBean</managed-bean-scope>
    <!--oracle-jdev-comment:managed-bean-jsp-link:1DanhucDonViBanHang.jspx-->
  </managed-bean>
  <managed-bean id="__7">
    <managed-bean-name>backing_ChungTuMuaHang</managed-bean-name>
    <managed-bean-class>view.backing.ChungTuMuaHang</managed-bean-class>
    <managed-bean-scope>backingBean</managed-bean-scope>
    <!--oracle-jdev-comment:managed-bean-jsp-link:1ChungTuMuaHang.jspx-->
  </managed-bean>
</adfc-config>
